televiewshka/__init__.py
televiewshka/adaptors.py
televiewshka/base.py
televiewshka/layouts.py
televiewshka/render.py
televiewshka/thoughts.py
televiewshka/type_aliases.py
televiewshka/utils.py
televiewshka/views.py
televiewshka/storage/base.py
televiewshka-0.0.1.dist-info/LICENSE
televiewshka-0.0.1.dist-info/METADATA
televiewshka-0.0.1.dist-info/WHEEL
televiewshka-0.0.1.dist-info/top_level.txt
televiewshka-0.0.1.dist-info/RECORD
