Metadata-Version: 2.1
Name: televiewshka
Version: 0.0.1
Summary: A framework to develop UI & logic for telegram bots with class based views
Home-page: https://github.com/akim-mukhtarov/televiewshka
Author: Akim Mukhtarov
Author-email: akim.int80h@gmail.com
Classifier: Programming Language :: Python
Classifier: Programming Language :: Python :: 3
Classifier: Programming Language :: Python :: 3 :: Only
Classifier: Intended Audience :: Developers
Classifier: License :: OSI Approved :: MIT License
Classifier: Operating System :: OS Independent
Classifier: Topic :: Software Development :: Libraries :: Python Modules
License-File: LICENSE
